hdfset/__init__.py
hdfset/base.py
hdfset/dataset.py
hdfset/py.typed
hdfset-0.3.0.dist-info/METADATA
hdfset-0.3.0.dist-info/WHEEL
hdfset-0.3.0.dist-info/licenses/LICENSE
hdfset-0.3.0.dist-info/RECORD
