Metadata-Version: 2.4
Name: hdfset
Version: 0.3.0
Summary: A Python package for reading and writing HDF5 files.
Project-URL: Documentation, https://github.com/daizutabi/hdfset
Project-URL: Source, https://github.com/daizutabi/hdfset
Project-URL: Issues, https://github.com/daizutabi/hdfset/issues
Author-email: daizutabi <daizutabi@gmail.com>
License: MIT License
License-File: LICENSE
Classifier: Programming Language :: Python
Classifier: Programming Language :: Python :: 3.10
Classifier: Programming Language :: Python :: 3.11
Classifier: Programming Language :: Python :: 3.12
Classifier: Programming Language :: Python :: 3.13
Requires-Python: >=3.10
Requires-Dist: pandas>=2
Requires-Dist: tables>=3
